README.md
setup.py
edgehub/__init__.py
edgehub/base.py
edgehub/exceptions.py
edgehub/node.py
edgehub.egg-info/PKG-INFO
edgehub.egg-info/SOURCES.txt
edgehub.egg-info/dependency_links.txt
edgehub.egg-info/requires.txt
edgehub.egg-info/top_level.txt
edgehub/master/__init__.py
edgehub/master/master.py
edgehub/master/node_info.py
edgehub/master/signal/__init__.py
edgehub/master/signal/sig_event.py
edgehub/master/signal/sig_queue.py
edgehub/master/signal/sig_sys.py
edgehub/util/__init__.py
edgehub/util/kill.py
edgehub/util/loghandle.py
edgehub/util/net.py