Metadata-Version: 2.1
Name: edgehub
Version: 0.0.1.dev0
Summary: A flexible and efficient cross process distributed edge computing engine.
Home-page: https://github.com/EdgeGalaxy/edgehub
Author: DannyLee1991
Author-email: 747554505@qq.com
License: GPLv3
Platform: UNKNOWN
Classifier: Programming Language :: Python :: 3
Classifier: License :: OSI Approved :: GNU General Public License v3 (GPLv3)
Classifier: Operating System :: OS Independent
Requires-Python: >=3.6.9
